http_request_response/__init__.py
http_request_response/exception.py
http_request_response/logging_manager.py
http_request_response-0.0.25.dist-info/LICENSE
http_request_response-0.0.25.dist-info/METADATA
http_request_response-0.0.25.dist-info/WHEEL
http_request_response-0.0.25.dist-info/top_level.txt
http_request_response-0.0.25.dist-info/RECORD
