Metadata-Version: 2.1
Name: http-request-response
Version: 0.0.25
Summary: The main target of this library is to standardize the request response in case of using flask-restplus library.
Home-page: https://github.com/Quakingaspen-codehub/http_request_response
Author: Quaking Aspen
Author-email: info@quakingaspen.net
License: MIT
Platform: UNKNOWN
Classifier: Programming Language :: Python :: 3
Classifier: License :: OSI Approved :: MIT License
Classifier: Operating System :: OS Independent
Requires-Python: >=3.6
License-File: LICENSE
Requires-Dist: http-status-code (>=0.0.10)
